{
  "coverage": "0%",
  "expectCount": 4,
  "actualCount": 0,
  "files": {
    "src/bisect_left.js": {
      "expectCount": 1,
      "actualCount": 0,
      "undocumentLines": [
        3
      ]
    },
    "src/bisect_right.js": {
      "expectCount": 1,
      "actualCount": 0,
      "undocumentLines": [
        3
      ]
    },
    "src/insort_left.js": {
      "expectCount": 1,
      "actualCount": 0,
      "undocumentLines": [
        3
      ]
    },
    "src/insort_right.js": {
      "expectCount": 1,
      "actualCount": 0,
      "undocumentLines": [
        3
      ]
    }
  }
}